README.rst
setup.py
mmsim/__init__.py
mmsim/commands.py
mmsim/download.py
mmsim/graphics.py
mmsim/mazes.py
mmsim/typing.py
mmsim/ui.py
mmsim.egg-info/PKG-INFO
mmsim.egg-info/SOURCES.txt
mmsim.egg-info/dependency_links.txt
mmsim.egg-info/entry_points.txt
mmsim.egg-info/requires.txt
mmsim.egg-info/top_level.txt