Metadata-Version: 2.1
Name: mmsim
Version: 0.1.6
Summary: A simple Micromouse Maze Simulator server
Home-page: https://github.com/Theseus/mmsim
Author: Miguel Sánchez de León Peque
Author-email: peque@neosit.es
License: BSD License
Keywords: micromouse maze server simulator
Platform: UNKNOWN
Classifier: Development Status :: 3 - Alpha
Classifier: Topic :: Utilities
Classifier: License :: OSI Approved :: BSD License
Classifier: Programming Language :: Python :: 3
Classifier: Programming Language :: Python :: 3.6
Classifier: Programming Language :: Python :: Implementation :: CPython
Provides-Extra: lint
Provides-Extra: test
Provides-Extra: docs
